mreventloop/__init__.py
mreventloop/attr.py
mreventloop/broker.py
mreventloop/connect.py
mreventloop/decorators.py
mreventloop/event_loop.py
mreventloop/events.py
mreventloop/make_awaitable.py
mreventloop/names.py
mreventloop/peer.py
mreventloop/slot_call.py
mreventloop/spy.py
mreventloop/sync_event.py
mreventloop/worker.py
MrEventLoop-0.7.1.dist-info/LICENSE
MrEventLoop-0.7.1.dist-info/METADATA
MrEventLoop-0.7.1.dist-info/WHEEL
MrEventLoop-0.7.1.dist-info/top_level.txt
MrEventLoop-0.7.1.dist-info/RECORD
