Metadata-Version: 2.1
Name: MrEventLoop
Version: 0.7.1
Summary: Simple event system working seamlessly across sockets
Author-email: Ole Kliemann <mail@olekliemann.de>
License: 
Project-URL: homepage, https://github.com/olekli/MrEventLoop
Classifier: Programming Language :: Python :: 3
Classifier: License :: OSI Approved :: Apache Software License
Classifier: Operating System :: OS Independent
Classifier: Development Status :: 4 - Beta
Classifier: Intended Audience :: Developers
Requires-Python: >=3.6
License-File: LICENSE
Requires-Dist: pyzmq ==25.1.2
Requires-Dist: jsonrpcclient ==4.0.3
Requires-Dist: jsonrpcserver ==5.0.9
